{
  "skill": "levelrpg:artificing",
  "title": "Artificing Mastery",
  "summary": "Artificing develops into either efficient workshop throughput or higher-complexity invention. Threshold pacing keeps each unlock tied to visible technical growth.",
  "minRank": 1,
  "nodes": [
    {
      "id": "artificing_wand_of_the_artificer",
      "title": "Wand of The Artificer",
      "description": "A complex tool with many complex functions.\n+1 Tool Slot\n\nBuilder’s Instinct\n\nConsecutive block placement slightly increases placement speed",
      "type": "core",
      "cost": 1,
      "requiredRank": 0,
      "layoutX": 0,
      "layoutY": 0,
      "requirement": {
        "mode": "all",
        "nodes": []
      }
    },
    {
      "id": "artificing_measuring_tape",
      "title": "Measuring Tape",
      "description": "Quickly assess block dimensions",
      "type": "trait",
      "cost": 1,
      "requiredRank": 0,
      "layoutX": 0,
      "layoutY": -62,
      "requirement": {
        "mode": "all",
        "nodes": [
          "artificing_wand_of_the_artificer",
          "artificing_line_tool"
        ]
      },
      "requires": [
        "artificing_wand_of_the_artificer",
        "artificing_line_tool"
      ]
    },
    {
      "id": "artificing_line_tool",
      "title": "Line Tool",
      "description": "Select two points → fills a straight line\nConstraints:\n limited max length (e.g. 16–32)\n requires sufficient materials",
      "type": "trait",
      "cost": 1,
      "requiredRank": 0,
      "layoutX": -63,
      "layoutY": -62,
      "requirement": {
        "mode": "all",
        "nodes": [
          "artificing_wand_of_the_artificer"
        ]
      },
      "requires": [
        "artificing_wand_of_the_artificer"
      ]
    },
    {
      "id": "artificing_replace_tool",
      "title": "Replace Tool",
      "description": "Replace blocks you placed with another block type",
      "type": "trait",
      "cost": 1,
      "requiredRank": 0,
      "layoutX": 0,
      "layoutY": -126,
      "requirement": {
        "mode": "all",
        "nodes": [
          "artificing_measuring_tape",
          "artificing_rotate_tool"
        ]
      },
      "requires": [
        "artificing_measuring_tape",
        "artificing_rotate_tool"
      ]
    },
    {
      "id": "artificing_rotate_tool",
      "title": "Rotate Tool",
      "description": "Rotate placed blocks\n",
      "type": "trait",
      "cost": 1,
      "requiredRank": 0,
      "layoutX": -63,
      "layoutY": -126,
      "requirement": {
        "mode": "all",
        "nodes": [
          "artificing_line_tool"
        ]
      },
      "requires": [
        "artificing_line_tool"
      ]
    },
    {
      "id": "artificing_smart_scaffolding",
      "title": "Smart Scaffolding",
      "description": "While holding jump, automatically places scaffolding from inventory beneath you and extends as you move upward",
      "type": "trait",
      "cost": 1,
      "requiredRank": 0,
      "layoutX": -63,
      "layoutY": -189,
      "requirement": {
        "mode": "all",
        "nodes": [
          "artificing_rotate_tool"
        ]
      },
      "requires": [
        "artificing_rotate_tool"
      ]
    },
    {
      "id": "artificing_block_swap",
      "title": "Block Swap",
      "description": "Swap two blocks with each other\n",
      "type": "trait",
      "cost": 1,
      "requiredRank": 0,
      "layoutX": 0,
      "layoutY": -189,
      "requirement": {
        "mode": "all",
        "nodes": [
          "artificing_replace_tool",
          "artificing_smart_scaffolding"
        ]
      },
      "requires": [
        "artificing_replace_tool",
        "artificing_smart_scaffolding"
      ]
    },
    {
      "id": "artificing_reach_extension",
      "title": "Reach Extension",
      "description": "Place blocks up to +3 blocks further\n",
      "type": "trait",
      "cost": 1,
      "requiredRank": 0,
      "layoutX": -63,
      "layoutY": -253,
      "requirement": {
        "mode": "all",
        "nodes": [
          "artificing_smart_scaffolding"
        ]
      },
      "requires": [
        "artificing_smart_scaffolding"
      ]
    },
    {
      "id": "artificing_fill_tool",
      "title": "Fill Tool",
      "description": "Attempt to fill in an area with a block\n",
      "type": "trait",
      "cost": 1,
      "requiredRank": 0,
      "layoutX": 0,
      "layoutY": -253,
      "requirement": {
        "mode": "all",
        "nodes": [
          "artificing_block_swap",
          "artificing_reach_extension"
        ]
      },
      "requires": [
        "artificing_block_swap",
        "artificing_reach_extension"
      ]
    },
    {
      "id": "artificing_weaver",
      "title": "Weaver",
      "description": "Two tools can merge into a new composite behavior",
      "type": "trait",
      "cost": 1,
      "requiredRank": 0,
      "layoutX": -31,
      "layoutY": -318,
      "requirement": {
        "mode": "all",
        "nodes": [
          "artificing_reach_extension",
          "artificing_fill_tool"
        ]
      },
      "requires": [
        "artificing_reach_extension",
        "artificing_fill_tool"
      ]
    },
    {
      "id": "artificing_tool_saver",
      "title": "Tool Saver",
      "description": "Reduced durability loss breaking blocks you placed",
      "type": "trait",
      "cost": 1,
      "requiredRank": 0,
      "layoutX": 97,
      "layoutY": -62,
      "requirement": {
        "mode": "all",
        "nodes": [
          "artificing_wand_of_the_artificer"
        ]
      },
      "requires": [
        "artificing_wand_of_the_artificer"
      ]
    },
    {
      "id": "artificing_trash_slot",
      "title": "Trash Slot",
      "description": "Items placed here are destroyed instantly",
      "type": "trait",
      "cost": 1,
      "requiredRank": 0,
      "layoutX": 160,
      "layoutY": -62,
      "requirement": {
        "mode": "all",
        "nodes": [
          "artificing_tool_saver",
          "artificing_wand_of_the_artificer"
        ]
      },
      "requires": [
        "artificing_tool_saver",
        "artificing_wand_of_the_artificer"
      ]
    },
    {
      "id": "artificing_compactor_slot",
      "title": "Compactor Slot",
      "description": "A dedicated slot that automatically converts specific items into compacted forms",
      "type": "trait",
      "cost": 1,
      "requiredRank": 0,
      "layoutX": 225,
      "layoutY": -62,
      "requirement": {
        "mode": "all",
        "nodes": [
          "artificing_trash_slot"
        ]
      },
      "requires": [
        "artificing_trash_slot"
      ]
    },
    {
      "id": "artificing_salvage_slot",
      "title": "Salvage Slot",
      "description": "Breaks items down into base materials",
      "type": "trait",
      "cost": 1,
      "requiredRank": 0,
      "layoutX": 225,
      "layoutY": -126,
      "requirement": {
        "mode": "all",
        "nodes": [
          "artificing_compactor_slot"
        ]
      },
      "requires": [
        "artificing_compactor_slot"
      ]
    },
    {
      "id": "artificing_manual_overclock",
      "title": "Manual Overclock",
      "description": "Interact with a machine:\n boosts speed for X seconds\n applies cooldown",
      "type": "trait",
      "cost": 1,
      "requiredRank": 0,
      "layoutX": 160,
      "layoutY": -126,
      "requirement": {
        "mode": "all",
        "nodes": [
          "artificing_trash_slot"
        ]
      },
      "requires": [
        "artificing_trash_slot"
      ]
    },
    {
      "id": "artificing_focused_operation",
      "title": "Focused Operation",
      "description": "While actively using a machine:\n slightly increased speed\n",
      "type": "trait",
      "cost": 1,
      "requiredRank": 0,
      "layoutX": 97,
      "layoutY": -126,
      "requirement": {
        "mode": "all",
        "nodes": [
          "artificing_tool_saver"
        ]
      },
      "requires": [
        "artificing_tool_saver"
      ]
    },
    {
      "id": "artificing_builders_cache",
      "title": "Builder’s Cache",
      "description": "Pull blocks automatically from inventory while building",
      "type": "trait",
      "cost": 1,
      "requiredRank": 0,
      "layoutX": 97,
      "layoutY": -189,
      "requirement": {
        "mode": "all",
        "nodes": [
          "artificing_focused_operation"
        ]
      },
      "requires": [
        "artificing_focused_operation"
      ]
    },
    {
      "id": "artificing_multi_mode_handling",
      "title": "Multi-Mode Handling",
      "description": "+1 Tool Slot",
      "type": "trait",
      "cost": 1,
      "requiredRank": 0,
      "layoutX": 160,
      "layoutY": -189,
      "requirement": {
        "mode": "all",
        "nodes": [
          "artificing_builders_cache"
        ]
      },
      "requires": [
        "artificing_builders_cache"
      ]
    },
    {
      "id": "artificing_mechanist",
      "title": "Mechanist",
      "description": "+1 Tool Slot\n",
      "type": "manifestation",
      "cost": 1,
      "requiredRank": 0,
      "layoutX": 160,
      "layoutY": -253,
      "requirement": {
        "mode": "all",
        "nodes": [
          "artificing_multi_mode_handling"
        ]
      },
      "requires": [
        "artificing_multi_mode_handling"
      ]
    },
    {
      "id": "artificing_quick_access",
      "title": "Quick Access",
      "description": "Reopen last interacted machine instantly",
      "type": "trait",
      "cost": 1,
      "requiredRank": 0,
      "layoutX": 97,
      "layoutY": -253,
      "requirement": {
        "mode": "all",
        "nodes": [
          "artificing_builders_cache"
        ]
      },
      "requires": [
        "artificing_builders_cache"
      ]
    },
    {
      "id": "artificing_architect",
      "title": "Architect",
      "description": "Quick Access becomes a persistent recall system\n",
      "type": "trait",
      "cost": 1,
      "requiredRank": 0,
      "layoutX": 97,
      "layoutY": -318,
      "requirement": {
        "mode": "all",
        "nodes": [
          "artificing_quick_access"
        ]
      },
      "requires": [
        "artificing_quick_access"
      ]
    }
  ]
}